{
    "Ar36": {
        "error": 0.00038005452882533487,
        "error_type": "SEM",
        "filter_outliers_dict": {
            "filter_outliers": true,
            "iterations": 1,
            "std_devs": 3,
            "use_iqr_filtering": false,
            "use_standard_deviation_filtering": false
        },
        "fit": "Linear",
        "fn": 123,
        "include_baseline_error": true,
        "n": 124,
        "outlier_excluded": [
            0
        ],
        "reviewed": true,
        "user_excluded": [],
        "value": 0.017475792405369454
    },
    "Ar37": {
        "error": 0.011743034861834103,
        "error_type": "SEM",
        "filter_outliers_dict": {
            "filter_outliers": true,
            "iterations": 1,
            "std_devs": 3,
            "use_iqr_filtering": false,
            "use_standard_deviation_filtering": false
        },
        "fit": "Linear",
        "fn": 123,
        "include_baseline_error": true,
        "n": 124,
        "outlier_excluded": [
            62
        ],
        "reviewed": true,
        "user_excluded": [],
        "value": -0.013562210061646412
    },
    "Ar38": {
        "error": 0.005903040591482943,
        "error_type": "SEM",
        "filter_outliers_dict": {
            "filter_outliers": true,
            "iterations": 1,
            "std_devs": 3,
            "use_iqr_filtering": false,
            "use_standard_deviation_filtering": false
        },
        "fit": "Linear",
        "fn": 122,
        "include_baseline_error": true,
        "n": 124,
        "outlier_excluded": [
            0,
            1
        ],
        "reviewed": true,
        "user_excluded": [],
        "value": 0.10958447013805729
    },
    "Ar39": {
        "error": 0.014133975738296386,
        "error_type": "SEM",
        "filter_outliers_dict": {
            "filter_outliers": true,
            "iterations": 1,
            "std_devs": 3,
            "use_iqr_filtering": false,
            "use_standard_deviation_filtering": false
        },
        "fit": "Linear",
        "fn": 122,
        "include_baseline_error": true,
        "n": 124,
        "outlier_excluded": [
            0,
            1
        ],
        "reviewed": true,
        "user_excluded": [],
        "value": 5.0582181982359
    },
    "Ar40": {
        "error": 0.02249800473255267,
        "error_type": "SEM",
        "filter_outliers_dict": {
            "filter_outliers": true,
            "iterations": 1,
            "std_devs": 3,
            "use_iqr_filtering": false,
            "use_standard_deviation_filtering": false
        },
        "fit": "Linear",
        "fn": 123,
        "include_baseline_error": true,
        "n": 124,
        "outlier_excluded": [
            11
        ],
        "reviewed": true,
        "user_excluded": [],
        "value": 68.47952808181766
    },
    "Ar41": {
        "error": 0.0033536362075040575,
        "error_type": "SEM",
        "filter_outliers_dict": {
            "filter_outliers": true,
            "iterations": 1,
            "std_devs": 2
        },
        "fit": "Average",
        "value": 0.03527580589914014
    }
}